copyablemodeladmin/__init__.py
copyablemodeladmin/helpers.py
copyablemodeladmin/options.py
copyablemodeladmin/views.py
copyablemodeladmin/tests/__init__.py
copyablemodeladmin/tests/settings.py
copyablemodeladmin/tests/test_options.py
copyablemodeladmin/tests/urls.py
copyablemodeladmin/tests/copyabletestapp/__init__.py
copyablemodeladmin/tests/copyabletestapp/models.py
copyablemodeladmin/tests/copyabletestapp/wagtail_hooks.py
wagtail_copyablemodeladmin-1.0.0.dist-info/LICENSE
wagtail_copyablemodeladmin-1.0.0.dist-info/METADATA
wagtail_copyablemodeladmin-1.0.0.dist-info/WHEEL
wagtail_copyablemodeladmin-1.0.0.dist-info/top_level.txt
wagtail_copyablemodeladmin-1.0.0.dist-info/RECORD
