Metadata-Version: 2.1
Name: wagtail-copyablemodeladmin
Version: 1.0.0
Summary: Copyable ModelAdmins for Django models used on Wagtail Sites
Home-page: https://github.com/cfpb/wagtail-copyablemodeladmin
Author: CFPB
Author-email: tech@cfpb.gov
License: CC0
Platform: UNKNOWN
Classifier: Framework :: Django
Classifier: Framework :: Django :: 1.11
Classifier: Framework :: Django :: 2.0
Classifier: Framework :: Django :: 2.1
Classifier: Framework :: Django :: 2.2
Classifier: Framework :: Wagtail
Classifier: Framework :: Wagtail :: 1
Classifier: Framework :: Wagtail :: 2
Classifier: License :: CC0 1.0 Universal (CC0 1.0) Public Domain Dedication
Classifier: License :: Public Domain
Classifier: Programming Language :: Python
Classifier: Programming Language :: Python :: 3
Classifier: Programming Language :: Python :: 3.6
Classifier: Programming Language :: Python :: 3.7
Requires-Dist: wagtail (<2.8,>=1.13)
Provides-Extra: testing
Requires-Dist: coverage (>=3.7.0) ; extra == 'testing'
Requires-Dist: model-mommy (>=2.0.0) ; extra == 'testing'
